{
  "id": "7723406332",
  "title": "U.S. Secretary of State Hillary Rodham Clinton poses for a photo with recipients of the U.S. State Department\u2019s 2011 Human Rights Defender Award including Adrian Jjuuko, Geoffrey Ogwaro, Julius Kaggwa, Joanita Warry Nambirige, Clare Byarugaba, Frank Mugis",
  "url": "https://live.staticflickr.com/7265/7723406332_3c853cb47e_b.jpg",
  "owner": "54621517@N08",
  "owner_name": "",
  "date_taken": "",
  "tags": "",
  "license": "4",
  "category": "friends group photo"
}