{
  "id": "6137311792",
  "title": "Their moment",
  "url": "https://live.staticflickr.com/6082/6137311792_0139af9fcf_b.jpg",
  "owner": "30588093@N06",
  "owner_name": "",
  "date_taken": "",
  "tags": "ocean park street city trip family blue girls friends light sunset sea party summer portrait sky people urban blackandwhite bw music woman sun white holiday black flower color tree cute sexy green bird art fall love film beach me nature beer girl smile car sunglasses smiling fashion birds festival kids night clouds laughing canon landscape fun happy photography glasses photo dance spring concert funny pretty day photos cigarette live smoke band atmosphere babe shades laugh",
  "license": "4",
  "category": "travel photography people"
}